reloadex/__init__.py
reloadex/__main__.py
reloadex/reloader.py
reloadex/test_cmdline_arguments.py
reloadex/test_run_linux.py
reloadex/test_run_uwsgi.py
reloadex/common/__init__.py
reloadex/common/utils_app_starter.py
reloadex/common/utils_reloader.py
reloadex/linux/__init__.py
reloadex/linux/_app_starter.py
reloadex/linux/reloader_linux.py
reloadex/linux/reloader_uwsgi.py
reloadex/linux/shared.py
reloadex/linux/ctypes_wrappers/__init__.py
reloadex/linux/ctypes_wrappers/_eventfd.py
reloadex/linux/ctypes_wrappers/_inotify.py
reloadex/linux/ctypes_wrappers/_posix_spawn.py
reloadex/linux/ctypes_wrappers/_prctl.py
reloadex/linux/ctypes_wrappers/_signalfd.py
reloadex/linux/ctypes_wrappers/_timerfd.py
reloadex/linux/ctypes_wrappers/common.py
reloadex/windows/__init__.py
reloadex/windows/_app_starter.py
reloadex/windows/reloader_windows.py
reloadex-0.6.dist-info/LICENSE.txt
reloadex-0.6.dist-info/METADATA
reloadex-0.6.dist-info/WHEEL
reloadex-0.6.dist-info/entry_points.txt
reloadex-0.6.dist-info/top_level.txt
reloadex-0.6.dist-info/RECORD
