Metadata-Version: 2.1
Name: reloadex
Version: 0.6
Summary: Restart WSGI server on code changes
Home-page: https://github.com/iljau/reloadex
Author: Ilja Umov
Author-email: 
License: MIT
Keywords: reload wsgi
Platform: UNKNOWN
Classifier: Development Status :: 4 - Beta
Classifier: Intended Audience :: Developers
Classifier: License :: OSI Approved :: MIT License
Classifier: Operating System :: POSIX :: Linux
Classifier: Operating System :: Microsoft :: Windows
Classifier: Programming Language :: Python :: 3.6
Classifier: Programming Language :: Python :: 3.7
Classifier: Topic :: Internet :: WWW/HTTP :: WSGI
Requires-Dist: pathspec (>=0.5.9)
Requires-Dist: pywin32 ; platform_system == "Windows"
Provides-Extra: dev
Requires-Dist: flask ; extra == 'dev'
Requires-Dist: uwsgi ; extra == 'dev'
Requires-Dist: waitress ; extra == 'dev'
